python_yamldoc-0.3.0.dist-info/DESCRIPTION.rst
python_yamldoc-0.3.0.dist-info/METADATA
python_yamldoc-0.3.0.dist-info/RECORD
python_yamldoc-0.3.0.dist-info/WHEEL
python_yamldoc-0.3.0.dist-info/metadata.json
python_yamldoc-0.3.0.dist-info/top_level.txt
yamldoc/__init__.py
yamldoc/_basedoc.py
yamldoc/_classdoc.py
yamldoc/_docfactory.py
yamldoc/_exceptions.py
yamldoc/_functiondoc.py
yamldoc/_inherit.py
yamldoc/_moduledoc.py
yamldoc/_propertydoc.py
yamldoc/_validate.py
yamldoc/_yaml.py
yamldoc/py3compat.py
