Metadata-Version: 2.0
Name: python-yamldoc
Version: 0.3.0
Summary: Take Python docstrings to the next level
Home-page: https://github.com/smathot/python-yamldoc
Author: Sebastiaan Mathot
Author-email: s.mathot@cogsci.nl
License: GNU GPL Version 3
Platform: UNKNOWN
Classifier: Development Status :: 4 - Beta
Classifier: Intended Audience :: Science/Research
Classifier: Topic :: Scientific/Engineering
Classifier: License :: OSI Approved :: GNU General Public License v3 (GPLv3)
Classifier: Programming Language :: Python :: 2
Classifier: Programming Language :: Python :: 3
